fastapi_static_digest/__init__.py
fastapi_static_digest/compiler.py
fastapi_static_digest/digest.py
fastapi_static_digest/settings.py
fastapi_static_digest-1.1.0.dist-info/LICENSE
fastapi_static_digest-1.1.0.dist-info/METADATA
fastapi_static_digest-1.1.0.dist-info/WHEEL
fastapi_static_digest-1.1.0.dist-info/top_level.txt
fastapi_static_digest-1.1.0.dist-info/RECORD
