Metadata-Version: 2.1
Name: fastapi-static-digest
Version: 1.1.0
Summary: Static file digest cache busting for FastAPI/Starlette
Home-page: UNKNOWN
Author: Tyler M Kontra
Author-email: tyler@tylerkontra.com
License: MIT
Project-URL: Source, https://github.com/ttymck/fastapi-static-digest
Platform: UNKNOWN
Classifier: Programming Language :: Python :: 3
Classifier: License :: OSI Approved :: MIT License
Classifier: Operating System :: OS Independent
Requires-Python: >=3.6
License-File: LICENSE
Requires-Dist: starlette
